py_deps/__init__.py
py_deps/cache.py
py_deps/deps.py
py_deps/exceptions.py
py_deps/graph.py
py_deps/logger.py
py_deps/tests/__init__.py
py_deps/tests/test_deps.py
py_deps/tests/test_graph.py
py_deps-1.0.1.dist-info/LICENSE
py_deps-1.0.1.dist-info/METADATA
py_deps-1.0.1.dist-info/WHEEL
py_deps-1.0.1.dist-info/top_level.txt
py_deps-1.0.1.dist-info/RECORD
