Metadata-Version: 2.1
Name: py-deps
Version: 1.0.1
Summary: parsing the Python deps and generating graph data
Home-page: https://github.com/mkouhei/py-deps
Author: Kouhei Maeda
Author-email: mkouhei@palmtb.net
License: GNU General Public License version 3
Platform: UNKNOWN
Classifier: Development Status :: 5 - Production/Stable
Classifier: Intended Audience :: Developers
Classifier: License :: OSI Approved :: GNU General Public License v3 or later (GPLv3+)
Classifier: Programming Language :: Python
Classifier: Programming Language :: Python :: 3
Classifier: Programming Language :: Python :: 3.8
Classifier: Programming Language :: Python :: Implementation :: CPython
Requires-Dist: networkx (==2.4)
Requires-Dist: pip (>=20.0)
Requires-Dist: setuptools (>=46.1)
Provides-Extra: memcache
Requires-Dist: pylibmc ; extra == 'memcache'
Provides-Extra: rest
Requires-Dist: Sphinx ; extra == 'rest'
